[{"title": "Airlines are not an 'investable business,' says former American Airlines CEO", "link": "https://www.cnbc.com/video/2020/05/04/american-airlines-ceo-investing-coronavirus-warren-buffett-response.html", "description": "Warren Buffett told investors Saturday that Berkshire Hathaway has sold its entire stakes in the four largest U.S. airlines \u2014 American, Delta, Southwest, United \u2014 as the pandemic upends another bet on the sector that the famed investor had shunned for years before a surprise return in 2016. Robert Crandall, former CEO of American Airlines and former chairman of the AMR Corporation, joins \"Squawk Box\" by phone to discuss.", "pubdate": "Mon, 04 May 2020 11:21:09 GMT", "author": null, "source": "CNBC_Travel"}]